pysfizz-0.1.2.dist-info/WHEEL
pysfizz-0.1.2.dist-info/METADATA
pysfizz-0.1.2.dist-info/RECORD
pysfizz-0.1.2.dist-info/licenses/LICENSE
pysfizz/synth.py
pysfizz/bindings.cpp
pysfizz/_sfizz.cpython-313-i386-linux-gnu.so
pysfizz/__init__.py
bin/sfizz_render
share/man/man1/sfizz_render.1
