Metadata-Version: 2.4
Name: pysfizz
Version: 0.1.2
Summary: Python bindings for sfizz
Keywords: audio,synthesis,sfz,sampler,music,sfizz
Author-Email: Haokun Tian <tianhaokun258@gmail.com>
License-Expression: BSD-2-Clause
License-File: LICENSE
Classifier: Development Status :: 3 - Alpha
Classifier: Intended Audience :: Developers
Classifier: Intended Audience :: Science/Research
Classifier: Topic :: Multimedia :: Sound/Audio :: Sound Synthesis
Classifier: Topic :: Software Development :: Libraries :: Python Modules
Classifier: Programming Language :: Python :: 3.9
Classifier: Programming Language :: Python :: 3.10
Classifier: Programming Language :: Python :: 3.11
Classifier: Programming Language :: Python :: 3.12
Classifier: Programming Language :: Python :: 3.13
Classifier: Operating System :: POSIX :: Linux
Classifier: Operating System :: MacOS
Classifier: Operating System :: Microsoft :: Windows
Project-URL: Source, https://github.com/tiianhk/pysfizz
Project-URL: Tracker, https://github.com/tiianhk/pysfizz/issues
Requires-Python: >=3.9
Requires-Dist: numpy
